evmole-0.8.2.dist-info/METADATA
evmole-0.8.2.dist-info/WHEEL
evmole/__init__.py
evmole/__init__.pyi
evmole/evmole.cp39-win_amd64.pyd
evmole/py.typed
evmole-0.8.2.dist-info/RECORD
