Metadata-Version: 2.4
Name: evmole
Version: 0.8.2
Summary: Extracts function selectors and arguments from EVM bytecode
Author: Maxim Andreev <andreevmaxim@gmail.com>
Author-email: Maxim Andreev <andreevmaxim@gmail.com>
License: MIT
Project-URL: Source Code, https://github.com/cdump/evmole
